autosolveclient/__init__.py
autosolveclient/autosolve.py
autosolveclient/testclient.py
autosolveclient-1.0.9.dist-info/METADATA
autosolveclient-1.0.9.dist-info/WHEEL
autosolveclient-1.0.9.dist-info/top_level.txt
autosolveclient-1.0.9.dist-info/RECORD
