Metadata-Version: 2.1
Name: autosolveclient
Version: 1.0.9
Summary: Client module for connecting to the Aycd Autosolve Network
Home-page: UNKNOWN
Author: Aycd Inc
Author-email: contact@aycd.io
License: UNKNOWN
Platform: UNKNOWN
Classifier: Programming Language :: Python :: 3
Classifier: License :: OSI Approved :: MIT License
Classifier: Operating System :: OS Independent
Requires-Python: >=3.6
Requires-Dist: pika
Requires-Dist: requests
Requires-Dist: logzero
Requires-Dist: pymitter
